.DS_Store
Spannotation/__init__.py
Spannotation/cli.py
Spannotation/mask_generator.py
spannotation-0.1.15.dist-info/LICENSE
spannotation-0.1.15.dist-info/METADATA
spannotation-0.1.15.dist-info/WHEEL
spannotation-0.1.15.dist-info/top_level.txt
spannotation-0.1.15.dist-info/RECORD
